spacy_to_hf/__init__.py
spacy_to_hf/conversion.py
spacy_to_hf/utils.py
spacy_to_hf-0.0.4.dist-info/LICENSE
spacy_to_hf-0.0.4.dist-info/METADATA
spacy_to_hf-0.0.4.dist-info/WHEEL
spacy_to_hf-0.0.4.dist-info/top_level.txt
spacy_to_hf-0.0.4.dist-info/RECORD
