Metadata-Version: 2.1
Name: spacy-to-hf
Version: 0.0.4
Summary: Spacy to HF converter
Author-email: Ben Epstein <ben.epstein97+spacy-hf@gmail.com>
License: Apache 2.0
Project-URL: Documentation, https://github.com/ben-epstein/spacy-to-hf
Requires-Python: <3.13,>=3.7
License-File: LICENSE
Requires-Dist: spacy-alignments
Requires-Dist: spacy<4
Requires-Dist: transformers
Requires-Dist: datasets
Requires-Dist: flax
Provides-Extra: dev
Requires-Dist: coverage>=6.1.1; extra == "dev"
Requires-Dist: invoke>=2.0.0; extra == "dev"
Requires-Dist: mypy>=0.910; extra == "dev"
Requires-Dist: packaging>=21.0; extra == "dev"
Requires-Dist: pre-commit>=2.17.0; extra == "dev"
Requires-Dist: pytest>=6.2.5; extra == "dev"
Requires-Dist: pytest-cov>=3.0.0; extra == "dev"
Requires-Dist: ruff>=0.0.98; extra == "dev"
Requires-Dist: build>=0.7.0; extra == "dev"
